config/sample_groups_list.json
config/sample_upload_order.txt
config/settings.yml
omero_adi/__init__.py
omero_adi/db_migrate.py
omero_adi/main.py
omero_adi/migrations/alembic.ini
omero_adi/migrations/env.py
omero_adi/migrations/script.py.mako
omero_adi/migrations/versions/78d3d6d84aec_add_description_to_imports.py
omero_adi/utils/__init__.py
omero_adi/utils/importer.py
omero_adi/utils/ingest_tracker.py
omero_adi/utils/initialize.py
omero_adi/utils/register.py
omero_adi/utils/upload_order_manager.py
omero_adi-1.0.0b4.dist-info/licenses/LICENCE
set_up/get_omero_info.py
tests/Barbie1.tif
tests/Barbie2.tif
tests/Barbie3.tif
tests/README.md
tests/requirements.txt
tests/setup_conda_test_env.sh
tests/system_check.py
tests/t_main.py
tests/t_settings.bak
tests/unittests/pyetest.ini
tests/unittests/test_ingest_tracker.py
tests/unittests/test_main.py
tests/unittests/test_upload_order_manager.py
tests/unittests/test_config/sample_groups_list.json
tests/unittests/test_config/sample_upload_order.txt
tests/unittests/test_config/settings.yml
tests/unittests/test_config/test.log
omero_adi-1.0.0b4.dist-info/METADATA
omero_adi-1.0.0b4.dist-info/WHEEL
omero_adi-1.0.0b4.dist-info/top_level.txt
omero_adi-1.0.0b4.dist-info/RECORD
